{"type":"FeatureCollection","features":[{"type":"Feature","properties":{"name":"E0 POR CORTE","molecula":"HO01","central":"HOLANDA","tipo":"E0"},"geometry":{"type":"Point","coordinates":[-74.16841497700972,4.629699709563097]}},{"type":"Feature","properties":{"name":"E1HO01_1","molecula":"HO01","central":"HOLANDA","tipo":"E1"},"geometry":{"type":"Point","coordinates":[-74.15627204546122,4.631643889801761]}},{"type":"Feature","properties":{"name":"E0 POR CORTE","molecula":"HO01","central":"HOLANDA","tipo":"E0"},"geometry":{"type":"Point","coordinates":[-74.1643610765842,4.632958636900957]}},{"type":"Feature","properties":{"name":"E0 POR CORTE","molecula":"HO01","central":"HOLANDA","tipo":"E0"},"geometry":{"type":"Point","coordinates":[-74.16381034578174,4.633461089487055]}},{"type":"Feature","properties":{"name":"E0 POR CORTE","molecula":"HO01","central":"HOLANDA","tipo":"E0"},"geometry":{"type":"Point","coordinates":[-74.16485061255392,4.632618833947583]}},{"type":"Feature","properties":{"name":"E0 POR CORTE","molecula":"HO01","central":"HOLANDA","tipo":"E0"},"geometry":{"type":"Point","coordinates":[-74.1677487477204,4.630278555217284]}},{"type":"Feature","properties":{"name":"E0 POR CORTE","molecula":"HO01","central":"HOLANDA","tipo":"E0"},"geometry":{"type":"Point","coordinates":[-74.16261426708665,4.633081575021272]}}]}