{"type":"FeatureCollection","features":[{"type":"Feature","properties":{"name":"E0 POR CORTE","molecula":"CO35","central":"CHICO","tipo":"E0"},"geometry":{"type":"Point","coordinates":[-74.07146573853767,4.663289330783722]}},{"type":"Feature","properties":{"name":"E0 POR CORTE","molecula":"CO35","central":"CHICO","tipo":"E0"},"geometry":{"type":"Point","coordinates":[-74.07278560848505,4.661427166475065]}},{"type":"Feature","properties":{"name":"E0 POR CORTE","molecula":"CO35","central":"CHICO","tipo":"E0"},"geometry":{"type":"Point","coordinates":[-74.06466832870751,4.661222789705207]}}]}