{"type":"FeatureCollection","features":[{"type":"Feature","properties":{"name":"E1HO02_1","molecula":"HO02","central":"HOLANDA","tipo":"E1"},"geometry":{"type":"Point","coordinates":[-74.16613026751418,4.620843338692112]}},{"type":"Feature","properties":{"name":"E1HO02_2","molecula":"HO02","central":"HOLANDA","tipo":"E1"},"geometry":{"type":"Point","coordinates":[-74.16896883904528,4.618661309275657]}},{"type":"Feature","properties":{"name":"E1HO02_3","molecula":"HO02","central":"HOLANDA","tipo":"E1"},"geometry":{"type":"Point","coordinates":[-74.16733447288283,4.616367933962822]}},{"type":"Feature","properties":{"name":"E1HO02_4","molecula":"HO02","central":"HOLANDA","tipo":"E1"},"geometry":{"type":"Point","coordinates":[-74.16918525410696,4.614966262572095]}},{"type":"Feature","properties":{"name":"EO POR CORTE","molecula":"HO02","central":"HOLANDA","tipo":"E0"},"geometry":{"type":"Point","coordinates":[-74.17202600893252,4.627635833854695]}},{"type":"Feature","properties":{"name":"EO POR CORTE","molecula":"HO02","central":"HOLANDA","tipo":"E0"},"geometry":{"type":"Point","coordinates":[-74.17202278321814,4.627634426011226]}},{"type":"Feature","properties":{"name":"E0 POR CORTE","molecula":"HO02","central":"HOLANDA","tipo":"E0"},"geometry":{"type":"Point","coordinates":[-74.17369227571847,4.626953487289938]}},{"type":"Feature","properties":{"name":"E0 POR CORTE","molecula":"HO02","central":"HOLANDA","tipo":"E0"},"geometry":{"type":"Point","coordinates":[-74.1702604858472,4.627545852374657]}},{"type":"Feature","properties":{"name":"E0 POR  CORTE","molecula":"HO02","central":"HOLANDA","tipo":"E0"},"geometry":{"type":"Point","coordinates":[-74.17062835546429,4.627851996503038]}}]}