{"type":"FeatureCollection","features":[{"type":"Feature","properties":{"name":"E0 POR CORTE","molecula":"TO36","central":"TOBERIN","tipo":"E0"},"geometry":{"type":"Point","coordinates":[-74.03241324131544,4.769735925875786]}},{"type":"Feature","properties":{"name":"E1TO36_3","molecula":"TO36","central":"TOBERIN","tipo":"E1"},"geometry":{"type":"Point","coordinates":[-74.04264521379534,4.771254285661022]}},{"type":"Feature","properties":{"name":"E2TO36_4","molecula":"TO36","central":"TOBERIN","tipo":"E0"},"geometry":{"type":"Point","coordinates":[-74.03248545250406,4.768300424180383]}},{"type":"Feature","properties":{"name":"E2TO36_5","molecula":"TO36","central":"TOBERIN","tipo":"E0"},"geometry":{"type":"Point","coordinates":[-74.0334959157244,4.76873434584181]}},{"type":"Feature","properties":{"name":"E1TO36_2","molecula":"TO36","central":"TOBERIN","tipo":"E1"},"geometry":{"type":"Point","coordinates":[-74.02968768493594,4.76571186558443]}}]}