{"type":"FeatureCollection","features":[{"type":"Feature","properties":{"name":"E0 POR CORTE","molecula":"SU13","central":"SUBA","tipo":"E0"},"geometry":{"type":"Point","coordinates":[-74.0852297886268,4.740142206366555]}}]}