{"type":"FeatureCollection","features":[{"type":"Feature","properties":{"name":"E0 POR CORTE","molecula":"CU11","central":"CUNI","tipo":"E0"},"geometry":{"type":"Point","coordinates":[-74.07071861479373,4.627010416332423]}}]}