{"type":"FeatureCollection","features":[{"type":"Feature","properties":{"name":"E0 POR CORTE","molecula":"HO07","central":"HOLANDA","tipo":"E0"},"geometry":{"type":"Point","coordinates":[-74.18464922843884,4.639412252439779]}}]}