{"type":"FeatureCollection","features":[{"type":"Feature","properties":{"name":"E1CO31_1","molecula":"CO31","central":"CHICO","tipo":"E1"},"geometry":{"type":"Point","coordinates":[-74.05974621573391,4.683786538938509]}},{"type":"Feature","properties":{"name":"E1CO31_2","molecula":"CO31","central":"CHICO","tipo":"E1"},"geometry":{"type":"Point","coordinates":[-74.06162331080743,4.682268654025094]}},{"type":"Feature","properties":{"name":"E1CO31_3","molecula":"CO31","central":"CHICO","tipo":"E1"},"geometry":{"type":"Point","coordinates":[-74.06483695028798,4.685310168997694]}},{"type":"Feature","properties":{"name":"E1CO31_4","molecula":"CO31","central":"CHICO","tipo":"E1"},"geometry":{"type":"Point","coordinates":[-74.06592404102368,4.68376749206001]}},{"type":"Feature","properties":{"name":"E1CO31_5","molecula":"CO31","central":"CHICO","tipo":"E1"},"geometry":{"type":"Point","coordinates":[-74.06780270595088,4.683372880217221]}},{"type":"Feature","properties":{"name":"E1CO31_6","molecula":"CO31","central":"CHICO","tipo":"E1"},"geometry":{"type":"Point","coordinates":[-74.06820166425288,4.686191392425023]}},{"type":"Feature","properties":{"name":"E0 POR CORTE","molecula":"CO31","central":"CHICO","tipo":"E0"},"geometry":{"type":"Point","coordinates":[-74.05866074404533,4.680824776812275]}},{"type":"Feature","properties":{"name":"E0 POR CORTE","molecula":"CO31","central":"CHICO","tipo":"E0"},"geometry":{"type":"Point","coordinates":[-74.05853009256957,4.680419569140318]}},{"type":"Feature","properties":{"name":"E0 POR CORTE","molecula":"CO31","central":"CHICO","tipo":"E0"},"geometry":{"type":"Point","coordinates":[-74.05790763308264,4.680226313944885]}}]}