{"type":"FeatureCollection","features":[{"type":"Feature","properties":{"name":"E0 POR CORTE","molecula":"TO38","central":"TOBERIN","tipo":"E0"},"geometry":{"type":"Point","coordinates":[-74.0305652783479,4.751000271116014]}}]}