{"type":"FeatureCollection","features":[{"type":"Feature","properties":{"name":"E1SI26_4","molecula":"SI26","central":"SANTA_INES","tipo":"E1"},"geometry":{"type":"Point","coordinates":[-74.0863972037147,4.537216047408064]}},{"type":"Feature","properties":{"name":"E0SI26_3","molecula":"SI26","central":"SANTA_INES","tipo":"E0"},"geometry":{"type":"Point","coordinates":[-74.0886760418941,4.537892887719312]}},{"type":"Feature","properties":{"name":"E1SI26_2","molecula":"SI26","central":"SANTA_INES","tipo":"E1"},"geometry":{"type":"Point","coordinates":[-74.09154907815359,4.539659406259732]}},{"type":"Feature","properties":{"name":"E1SI26_1","molecula":"SI26","central":"SANTA_INES","tipo":"E1"},"geometry":{"type":"Point","coordinates":[-74.08903102147173,4.539787008475076]}},{"type":"Feature","properties":{"name":"E0 POR CORTE","molecula":"SI26","central":"SANTA_INES","tipo":"E0"},"geometry":{"type":"Point","coordinates":[-74.08726226584328,4.558323784534339]}},{"type":"Feature","properties":{"name":"E0 POR CORTE","molecula":"SI26","central":"SANTA_INES","tipo":"E0"},"geometry":{"type":"Point","coordinates":[-74.08502899676046,4.552194970603731]}},{"type":"Feature","properties":{"name":"E0 POR CORTE","molecula":"SI26","central":"SANTA_INES","tipo":"E0"},"geometry":{"type":"Point","coordinates":[-74.0853807399382,4.553710043354835]}},{"type":"Feature","properties":{"name":"E0 POR CORTE","molecula":"SI26","central":"SANTA_INES","tipo":"E0"},"geometry":{"type":"Point","coordinates":[-74.0847876620866,4.552939939428082]}}]}