{"type":"FeatureCollection","features":[{"type":"Feature","properties":{"name":"E1SI09_1","molecula":"SI09","central":"SANTA_INES","tipo":"E1"},"geometry":{"type":"Point","coordinates":[-74.09369405742765,4.568160955256352]}},{"type":"Feature","properties":{"name":"E1SI09_2","molecula":"SI09","central":"SANTA_INES","tipo":"E1"},"geometry":{"type":"Point","coordinates":[-74.09634740014334,4.570760472449398]}},{"type":"Feature","properties":{"name":"E1SI09_3","molecula":"SI09","central":"SANTA_INES","tipo":"E1"},"geometry":{"type":"Point","coordinates":[-74.09862394931356,4.571680909287155]}},{"type":"Feature","properties":{"name":"E1SI09_4","molecula":"SI09","central":"SANTA_INES","tipo":"E1"},"geometry":{"type":"Point","coordinates":[-74.10555511566146,4.568753410017462]}},{"type":"Feature","properties":{"name":"E0 POR CORTE","molecula":"SI09","central":"SANTA_INES","tipo":"E0"},"geometry":{"type":"Point","coordinates":[-74.09298893172503,4.566120001522293]}},{"type":"Feature","properties":{"name":"EO POR CORTE","molecula":"SI09","central":"SANTA_INES","tipo":"E0"},"geometry":{"type":"Point","coordinates":[-74.09372451682621,4.567428821387805]}}]}