{"type":"FeatureCollection","features":[{"type":"Feature","properties":{"name":"E1CU25_4","molecula":"CU25","central":"CUNI","tipo":"E1"},"geometry":{"type":"Point","coordinates":[-74.07770102677698,4.609509715640632]}},{"type":"Feature","properties":{"name":"E1CU25_3","molecula":"CU25","central":"CUNI","tipo":"E1"},"geometry":{"type":"Point","coordinates":[-74.08395464453525,4.614307129376577]}},{"type":"Feature","properties":{"name":"E1CU25_2","molecula":"CU25","central":"CUNI","tipo":"E1"},"geometry":{"type":"Point","coordinates":[-74.0865732450349,4.616601518605796]}},{"type":"Feature","properties":{"name":"E1CU25_1","molecula":"CU25","central":"CUNI","tipo":"E1"},"geometry":{"type":"Point","coordinates":[-74.08671412221635,4.619970648496368]}},{"type":"Feature","properties":{"name":"E0 POR CORTE","molecula":"CU25","central":"CUNI","tipo":"E0"},"geometry":{"type":"Point","coordinates":[-74.08502507798939,4.615303559152665]}}]}