{"type":"FeatureCollection","features":[{"type":"Feature","properties":{"name":"E0 POR CORTE","molecula":"CU05","central":"CUNI","tipo":"E0"},"geometry":{"type":"Point","coordinates":[-74.1334512643045,4.609533972321648]}}]}