{"type":"FeatureCollection","features":[{"type":"Feature","properties":{"name":"E0 POR CORTE","molecula":"TO11","central":"TOBERIN","tipo":"E0"},"geometry":{"type":"Point","coordinates":[-74.04574643975184,4.725837411338214]}}]}