{"type":"FeatureCollection","features":[{"type":"Feature","properties":{"name":"E1HO18_4","molecula":"HO18","central":"HOLANDA","tipo":"E1"},"geometry":{"type":"Point","coordinates":[-74.186001065712,4.621266008298381]}},{"type":"Feature","properties":{"name":"E1HO18_3","molecula":"HO18","central":"HOLANDA","tipo":"E1"},"geometry":{"type":"Point","coordinates":[-74.18704909159248,4.622880471591375]}},{"type":"Feature","properties":{"name":"E1HO18_1","molecula":"HO18","central":"HOLANDA","tipo":"E1"},"geometry":{"type":"Point","coordinates":[-74.18411076346605,4.625076808362111]}},{"type":"Feature","properties":{"name":"E1HO18_2","molecula":"HO18","central":"HOLANDA","tipo":"E1"},"geometry":{"type":"Point","coordinates":[-74.18191252953888,4.624744295467656]}},{"type":"Feature","properties":{"name":"E1HO18_5","molecula":"HO18","central":"HOLANDA","tipo":"E1"},"geometry":{"type":"Point","coordinates":[-74.18130855516448,4.621905048486878]}},{"type":"Feature","properties":{"name":"E0 POR CORTE","molecula":"HO18","central":"HOLANDA","tipo":"E0"},"geometry":{"type":"Point","coordinates":[-74.18603503597552,4.618899433763055]}},{"type":"Feature","properties":{"name":"E0 POR  CORTE","molecula":"HO18","central":"HOLANDA","tipo":"E0"},"geometry":{"type":"Point","coordinates":[-74.18175066739775,4.621991583866391]}},{"type":"Feature","properties":{"name":"E0 POR CORTE","molecula":"HO18","central":"HOLANDA","tipo":"E0"},"geometry":{"type":"Point","coordinates":[-74.18632053316779,4.624187811129689]}},{"type":"Feature","properties":{"name":"E0 POR CORTE","molecula":"HO18","central":"HOLANDA","tipo":"E0"},"geometry":{"type":"Point","coordinates":[-74.18288165746807,4.623955598978052]}},{"type":"Feature","properties":{"name":"E0 POR CORTE","molecula":"HO18","central":"HOLANDA","tipo":"E0"},"geometry":{"type":"Point","coordinates":[-74.18218175125172,4.621551803757513]}}]}